LICENSE
MANIFEST.in
README.rst
setup.cfg
setup.py
johnny/__init__.py
johnny/cache.py
johnny/decorators.py
johnny/localstore.py
johnny/middleware.py
johnny/models.py
johnny/settings.py
johnny/signals.py
johnny/transaction.py
johnny/utils.py
johnny/backends/__init__.py
johnny/backends/filebased.py
johnny/backends/locmem.py
johnny/backends/memcached.py
johnny/backends/redis.py
johnny_cache.egg-info/PKG-INFO
johnny_cache.egg-info/SOURCES.txt
johnny_cache.egg-info/dependency_links.txt
johnny_cache.egg-info/not-zip-safe
johnny_cache.egg-info/top_level.txt