Metadata-Version: 1.0
Name: johnny-cache
Version: 1.4
Summary: Django caching framework that automatically caches all read queries.
Home-page: http://dev.jmoiron.net/johnny/
Author: Jason Moiron
Author-email: jmoiron@jmoiron.net
License: MIT
Keywords: django johnny cache
Platform: UNKNOWN
Classifier: Development Status :: 5 - Production/Stable
Classifier: Intended Audience :: Developers
Classifier: License :: OSI Approved :: MIT License
Classifier: Programming Language :: Python
Classifier: Operating System :: OS Independent
Classifier: Framework :: Django
Classifier: Topic :: Internet :: WWW/HTTP :: Dynamic Content
Classifier: Topic :: Software Development :: Libraries
Classifier: Topic :: Software Development :: Libraries :: Python Modules
